Account_logBASIC/__init__.py
account_log_basic-0.1.0.dist-info/METADATA
account_log_basic-0.1.0.dist-info/WHEEL
account_log_basic-0.1.0.dist-info/top_level.txt
account_log_basic-0.1.0.dist-info/RECORD
