Metadata-Version: 2.4
Name: Account_log_basic
Version: 0.1.0
Summary: A basic account login and creation module in Python
Home-page: https://github.com/yourusername/Account_log_basic
Author: Your Name
Author-email: your@email.com
Dynamic: author
Dynamic: author-email
Dynamic: description
Dynamic: description-content-type
Dynamic: home-page
Dynamic: summary
